krules_cloudevents/__init__.py
krules_cloudevents/dispatch_policy.py
krules_cloudevents/middleware.py
krules_cloudevents/publisher.py
krules_cloudevents/route/__init__.py
krules_cloudevents/route/dispatcher.py
krules_cloudevents_pubsub/__init__.py
krules_cloudevents_pubsub/dispatch_policy.py
krules_cloudevents_pubsub/middleware.py
krules_cloudevents_pubsub/publisher.py
krules_cloudevents_pubsub/subscriber.py
krules_cloudevents_pubsub/route/__init__.py
krules_cloudevents_pubsub/route/dispatcher.py
krules_core/__init__.py
krules_core/container.py
krules_core/event_bus.py
krules_core/event_types.py
krules_core/exceptions_dumpers.py
krules_core/handlers.py
krules_core/settings.py
krules_core/utils.py
krules_core/route/__init__.py
krules_core/route/dispatcher.py
krules_core/subject/__init__.py
krules_core/subject/empty_storage.py
krules_core/subject/storaged_subject.py
krules_fastapi_env/__init__.py
krules_fastapi_env/app.py
postgres_subjects_storage/__init__.py
postgres_subjects_storage/storage_impl.py
redis_subjects_storage/__init__.py
redis_subjects_storage/storage_impl.py
krules_framework-3.1.1.dist-info/METADATA
krules_framework-3.1.1.dist-info/WHEEL
krules_framework-3.1.1.dist-info/RECORD
