Metadata-Version: 2.4
Name: krules-framework
Version: 3.1.1
Summary: KRules Framework - Async event-driven framework
Author-email: Airspot <info@airspot.tech>
License: Apache-2.0
Keywords: async,event-driven,framework,krules,reactive
Classifier: Development Status :: 5 - Production/Stable
Classifier: Intended Audience :: Developers
Classifier: License :: OSI Approved :: Apache Software License
Classifier: Programming Language :: Python :: 3
Classifier: Programming Language :: Python :: 3.11
Classifier: Programming Language :: Python :: 3.12
Classifier: Programming Language :: Python :: 3.13
Classifier: Topic :: Software Development :: Libraries :: Application Frameworks
Requires-Python: >=3.11
Requires-Dist: dependency-injector==4.48.2
Requires-Dist: pydantic-settings>=2.11.0
Requires-Dist: redis>=6.4.0
Provides-Extra: dev
Requires-Dist: black>=23.0.0; extra == 'dev'
Requires-Dist: build>=1.0.3; extra == 'dev'
Requires-Dist: flake8>=7.0.0; extra == 'dev'
Requires-Dist: gitpython>=3.1.40; extra == 'dev'
Requires-Dist: httpx>=0.27.2; extra == 'dev'
Requires-Dist: invoke>=2.2.0; extra == 'dev'
Requires-Dist: isort>=5.0.0; extra == 'dev'
Requires-Dist: mkdocs-material>=9.0.0; extra == 'dev'
Requires-Dist: mkdocs>=1.5.0; extra == 'dev'
Requires-Dist: mkdocstrings[python]>=0.24.0; extra == 'dev'
Requires-Dist: mypy>=1.0.0; extra == 'dev'
Requires-Dist: pylint>=3.0.0; extra == 'dev'
Requires-Dist: pytest-cov>=4.0.0; extra == 'dev'
Requires-Dist: pytest-localserver>=0.9.0; extra == 'dev'
Requires-Dist: pytest>=7.0.0; extra == 'dev'
Requires-Dist: semver>=3.0.0; extra == 'dev'
Requires-Dist: toml>=0.10.2; extra == 'dev'
Requires-Dist: twine>=4.0.2; extra == 'dev'
Requires-Dist: types-pytz; extra == 'dev'
Requires-Dist: types-toml; extra == 'dev'
Provides-Extra: fastapi
Requires-Dist: fastapi>=0.115.4; extra == 'fastapi'
Requires-Dist: uvicorn>=0.32.0; extra == 'fastapi'
Provides-Extra: postgres
Requires-Dist: asyncpg>=0.30.0; extra == 'postgres'
Provides-Extra: pubsub
Requires-Dist: cloudevents==1.11.0; extra == 'pubsub'
Requires-Dist: google-cloud-pubsub>=2.26.1; extra == 'pubsub'
Provides-Extra: redis
Requires-Dist: redis>=5.2.0; extra == 'redis'
